<?xml version="1.0" encoding="UTF-8"?>
  <xml_result>
      <read_sentence lan="cn" type="study" version="7,0,0,1024">
          <rec_paper>
              <read_sentence accuracy_score="0.000000" beg_pos="0" content="还有。男人就应该负责任。我讨厌没有责任感的男人。遇到什么事先想到的总是自己。这样的人靠不住。我妈说我太理想化。可这种大事我可不想马马虎虎的。要找就找个称心如意的。你说是吧。" emotion_score="0.000000" end_pos="2373" except_info="0" fluency_score="89.518982" integrity_score="100.000000" is_rejected="false" phone_score="96.753250" time_len="2373" tone_score="84.415588" total_score="87.896439">
                  <sentence beg_pos="0" content="还有" end_pos="100" fluency_score="0.000000" phone_score="100.000000" time_len="100" tone_score="100.000000" total_score="92.398689">
                      <word beg_pos="0" content="还" end_pos="68" symbol="hai2" time_len="68">
                          <syll beg_pos="0" content="sil" dp_message="0" end_pos="3" rec_node_type="sil" time_len="3">
                              <phone beg_pos="0" content="sil" dp_message="0" end_pos="3" rec_node_type="sil" time_len="3"></phone>
                          </syll>
                          <syll beg_pos="3" content="还" dp_message="0" end_pos="68" rec_node_type="paper" symbol="hai2" time_len="65">
                              <phone beg_pos="3" content="h" dp_message="0" end_pos="52" is_yun="0" perr_level_msg="1" perr_msg="0" rec_node_type="paper" time_len="49"></phone>
                              <phone beg_pos="52" content="ai" dp_message="0" end_pos="68" is_yun="1" mono_tone="TONE2" perr_level_msg="1" perr_msg="0" rec_node_type="paper" time_len="16"></phone>
                          </syll>
                      </word>
                      <word beg_pos="68" content="有" end_pos="100" symbol="you3" time_len="32">
                          <syll beg_pos="68" content="有" dp_message="0" end_pos="100" rec_node_type="paper" symbol="you3" time_len="32">
                              <phone beg_pos="68" content="_i" dp_message="0" end_pos="75" is_yun="0" perr_level_msg="1" perr_msg="0" rec_node_type="paper" time_len="7"></phone>
                              <phone beg_pos="75" content="iou" dp_message="0" end_pos="100" is_yun="1" mono_tone="TONE3" perr_level_msg="1" perr_msg="0" rec_node_type="paper" time_len="25"></phone>
                          </syll>
                      </word>
                  </sentence>
                  <sentence beg_pos="100" content="男人就应该负责任" end_pos="386" fluency_score="0.000000" phone_score="100.000000" time_len="386" tone_score="100.000000" total_score="92.398689">
                      <word beg_pos="100" content="男" end_pos="160" symbol="nan2" time_len="60">
                          <syll beg_pos="100" content="sil" dp_message="0" end_pos="131" rec_node_type="sil" time_len="31">
                              <phone beg_pos="100" content="sil" dp_message="0" end_pos="131" rec_node_type="sil" time_len="31"></phone>
                          </syll>
                          <syll beg_pos="131" content="男" dp_message="0" end_pos="160" rec_node_type="paper" symbol="nan2" time_len="29">
                              <phone beg_pos="131" content="n" dp_message="0" end_pos="149" is_yun="0" perr_level_msg="1" perr_msg="0" rec_node_type="paper" time_len="18"></phone>
                              <phone beg_pos="149" content="an" dp_message="0" end_pos="160" is_yun="1" mono_tone="TONE2" perr_level_msg="1" perr_msg="0" rec_node_type="paper" time_len="11"></phone>
                          </syll>
                      </word>
                      <word beg_pos="160" content="人" end_pos="190" symbol="ren7" time_len="30">
                          <syll beg_pos="160" content="人" dp_message="0" end_pos="190" rec_node_type="paper" symbol="ren0" time_len="30">
                              <phone beg_pos="160" content="r" dp_message="0" end_pos="174" is_yun="0" perr_level_msg="1" perr_msg="0" rec_node_type="paper" time_len="14"></phone>
                              <phone beg_pos="174" content="en" dp_message="0" end_pos="190" is_yun="1" mono_tone="TONE0" perr_level_msg="1" perr_msg="0" rec_node_type="paper" time_len="16"></phone>
                          </syll>
                      </word>
                      <word beg_pos="190" content="就" end_pos="236" symbol="jiu4" time_len="46">
                          <syll beg_pos="190" content="就" dp_message="0" end_pos="236" rec_node_type="paper" symbol="jiu4" time_len="46">
                              <phone beg_pos="190" content="j" dp_message="0" end_pos="198" is_yun="0" perr_level_msg="1" perr_msg="0" rec_node_type="paper" time_len="8"></phone>
                              <phone beg_pos="198" content="iou" dp_message="0" end_pos="236" is_yun="1" mono_tone="TONE4" perr_level_msg="1" perr_msg="0" rec_node_type="paper" time_len="38"></phone>
                          </syll>
                      </word>
                      <word beg_pos="236" content="应" end_pos="266" symbol="ying1" time_len="30">
                          <syll beg_pos="236" content="应" dp_message="0" end_pos="266" rec_node_type="paper" symbol="ying1" time_len="30">
                              <phone beg_pos="236" content="_i" dp_message="0" end_pos="246" is_yun="0" perr_level_msg="1" perr_msg="0" rec_node_type="paper" time_len="10"></phone>
                              <phone beg_pos="246" content="ing" dp_message="0" end_pos="266" is_yun="1" mono_tone="TONE1" perr_level_msg="1" perr_msg="0" rec_node_type="paper" time_len="20"></phone>
                          </syll>
                      </word>
                      <word beg_pos="266" content="该" end_pos="288" symbol="gai1" time_len="22">
                          <syll beg_pos="266" content="该" dp_message="0" end_pos="288" rec_node_type="paper" symbol="gai1" time_len="22">
                              <phone beg_pos="266" content="g" dp_message="0" end_pos="274" is_yun="0" perr_level_msg="1" perr_msg="0" rec_node_type="paper" time_len="8"></phone>
                              <phone beg_pos="274" content="ai" dp_message="0" end_pos="288" is_yun="1" mono_tone="TONE1" perr_level_msg="1" perr_msg="0" rec_node_type="paper" time_len="14"></phone>
                          </syll>
                      </word>
                      <word beg_pos="288" content="负" end_pos="318" symbol="fu4" time_len="30">
                          <syll beg_pos="288" content="负" dp_message="0" end_pos="318" rec_node_type="paper" symbol="fu4" time_len="30">
                              <phone beg_pos="288" content="f" dp_message="0" end_pos="303" is_yun="0" perr_level_msg="1" perr_msg="0" rec_node_type="paper" time_len="15"></phone>
                              <phone beg_pos="303" content="u" dp_message="0" end_pos="318" is_yun="1" mono_tone="TONE4" perr_level_msg="1" perr_msg="0" rec_node_type="paper" time_len="15"></phone>
                          </syll>
                      </word>
                      <word beg_pos="318" content="责" end_pos="350" symbol="ze2" time_len="32">
                          <syll beg_pos="318" content="责" dp_message="0" end_pos="350" rec_node_type="paper" symbol="ze2" time_len="32">
                              <phone beg_pos="318" content="z" dp_message="0" end_pos="330" is_yun="0" perr_level_msg="1" perr_msg="0" rec_node_type="paper" time_len="12"></phone>
                              <phone beg_pos="330" content="e" dp_message="0" end_pos="350" is_yun="1" mono_tone="TONE2" perr_level_msg="1" perr_msg="0" rec_node_type="paper" time_len="20"></phone>
                          </syll>
                      </word>
                      <word beg_pos="350" content="任" end_pos="386" symbol="ren4" time_len="36">
                          <syll beg_pos="350" content="任" dp_message="0" end_pos="386" rec_node_type="paper" symbol="ren4" time_len="36">
                              <phone beg_pos="350" content="r" dp_message="0" end_pos="360" is_yun="0" perr_level_msg="1" perr_msg="0" rec_node_type="paper" time_len="10"></phone>
                              <phone beg_pos="360" content="en" dp_message="0" end_pos="386" is_yun="1" mono_tone="TONE4" perr_level_msg="1" perr_msg="0" rec_node_type="paper" time_len="26"></phone>
                          </syll>
                      </word>
                  </sentence>
                  <sentence beg_pos="386" content="我讨厌没有责任感的男人" end_pos="684" fluency_score="0.000000" phone_score="95.454544" time_len="684" tone_score="81.818184" total_score="92.398689">
                      <word beg_pos="386" content="我" end_pos="444" symbol="wo3" time_len="58">
                          <syll beg_pos="386" content="sil" dp_message="0" end_pos="398" rec_node_type="sil" time_len="12">
                              <phone beg_pos="386" content="sil" dp_message="0" end_pos="398" rec_node_type="sil" time_len="12"></phone>
                          </syll>
                          <syll beg_pos="398" content="我" dp_message="0" end_pos="444" rec_node_type="paper" symbol="wo3" time_len="46">
                              <phone beg_pos="398" content="_u" dp_message="0" end_pos="430" is_yun="0" perr_level_msg="1" perr_msg="0" rec_node_type="paper" time_len="32"></phone>
                              <phone beg_pos="430" content="uo" dp_message="0" end_pos="444" is_yun="1" mono_tone="TONE3" perr_level_msg="3" perr_msg="3" rec_node_type="paper" time_len="14"></phone>
                          </syll>
                      </word>
                      <word beg_pos="444" content="讨" end_pos="472" symbol="tao3" time_len="28">
                          <syll beg_pos="444" content="讨" dp_message="0" end_pos="472" rec_node_type="paper" symbol="tao3" time_len="28">
                              <phone beg_pos="444" content="t" dp_message="0" end_pos="456" is_yun="0" perr_level_msg="1" perr_msg="0" rec_node_type="paper" time_len="12"></phone>
                              <phone beg_pos="456" content="ao" dp_message="0" end_pos="472" is_yun="1" mono_tone="TONE3" perr_level_msg="1" perr_msg="0" rec_node_type="paper" time_len="16"></phone>
                          </syll>
                      </word>
                      <word beg_pos="472" content="厌" end_pos="493" symbol="yan4" time_len="21">
                          <syll beg_pos="472" content="厌" dp_message="0" end_pos="493" rec_node_type="paper" symbol="yan4" time_len="21">
                              <phone beg_pos="472" content="_i" dp_message="0" end_pos="480" is_yun="0" perr_level_msg="1" perr_msg="0" rec_node_type="paper" time_len="8"></phone>
                              <phone beg_pos="480" content="ian" dp_message="0" end_pos="493" is_yun="1" mono_tone="TONE4" perr_level_msg="1" perr_msg="0" rec_node_type="paper" time_len="13"></phone>
                          </syll>
                      </word>
                      <word beg_pos="493" content="没" end_pos="516" symbol="mei2" time_len="23">
                          <syll beg_pos="493" content="没" dp_message="0" end_pos="516" rec_node_type="paper" symbol="mei2" time_len="23">
                              <phone beg_pos="493" content="m" dp_message="0" end_pos="504" is_yun="0" perr_level_msg="1" perr_msg="0" rec_node_type="paper" time_len="11"></phone>
                              <phone beg_pos="504" content="ei" dp_message="0" end_pos="516" is_yun="1" mono_tone="TONE2" perr_level_msg="1" perr_msg="0" rec_node_type="paper" time_len="12"></phone>
                          </syll>
                      </word>
                      <word beg_pos="516" content="有" end_pos="538" symbol="you3" time_len="22">
                          <syll beg_pos="516" content="有" dp_message="0" end_pos="538" rec_node_type="paper" symbol="you3" time_len="22">
                              <phone beg_pos="516" content="_i" dp_message="0" end_pos="520" is_yun="0" perr_level_msg="1" perr_msg="0" rec_node_type="paper" time_len="4"></phone>
                              <phone beg_pos="520" content="iou" dp_message="0" end_pos="538" is_yun="1" mono_tone="TONE3" perr_level_msg="1" perr_msg="0" rec_node_type="paper" time_len="18"></phone>
                          </syll>
                      </word>
                      <word beg_pos="538" content="责" end_pos="564" symbol="ze2" time_len="26">
                          <syll beg_pos="538" content="责" dp_message="0" end_pos="564" rec_node_type="paper" symbol="ze2" time_len="26">
                              <phone beg_pos="538" content="z" dp_message="0" end_pos="548" is_yun="0" perr_level_msg="1" perr_msg="0" rec_node_type="paper" time_len="10"></phone>
                              <phone beg_pos="548" content="e" dp_message="0" end_pos="564" is_yun="1" mono_tone="TONE2" perr_level_msg="1" perr_msg="0" rec_node_type="paper" time_len="16"></phone>
                          </syll>
                      </word>
                      <word beg_pos="564" content="任" end_pos="586" symbol="ren4" time_len="22">
                          <syll beg_pos="564" content="任" dp_message="0" end_pos="586" rec_node_type="paper" symbol="ren4" time_len="22">
                              <phone beg_pos="564" content="r" dp_message="0" end_pos="571" is_yun="0" perr_level_msg="1" perr_msg="0" rec_node_type="paper" time_len="7"></phone>
                              <phone beg_pos="571" content="en" dp_message="0" end_pos="586" is_yun="1" mono_tone="TONE4" perr_level_msg="1" perr_msg="0" rec_node_type="paper" time_len="15"></phone>
                          </syll>
                      </word>
                      <word beg_pos="586" content="感" end_pos="612" symbol="gan3" time_len="26">
                          <syll beg_pos="586" content="感" dp_message="0" end_pos="612" rec_node_type="paper" symbol="gan3" time_len="26">
                              <phone beg_pos="586" content="g" dp_message="0" end_pos="594" is_yun="0" perr_level_msg="1" perr_msg="0" rec_node_type="paper" time_len="8"></phone>
                              <phone beg_pos="594" content="an" dp_message="0" end_pos="612" is_yun="1" mono_tone="TONE3" perr_level_msg="1" perr_msg="2" rec_node_type="paper" time_len="18"></phone>
                          </syll>
                      </word>
                      <word beg_pos="612" content="的" end_pos="626" symbol="de5" time_len="14">
                          <syll beg_pos="612" content="的" dp_message="0" end_pos="626" rec_node_type="paper" symbol="de0" time_len="14">
                              <phone beg_pos="612" content="d" dp_message="0" end_pos="616" is_yun="0" perr_level_msg="2" perr_msg="0" rec_node_type="paper" time_len="4"></phone>
                              <phone beg_pos="616" content="e" dp_message="0" end_pos="626" is_yun="1" mono_tone="TONE0" perr_level_msg="1" perr_msg="0" rec_node_type="paper" time_len="10"></phone>
                          </syll>
                      </word>
                      <word beg_pos="626" content="男" end_pos="652" symbol="nan2" time_len="26">
                          <syll beg_pos="626" content="男" dp_message="0" end_pos="652" rec_node_type="paper" symbol="nan2" time_len="26">
                              <phone beg_pos="626" content="n" dp_message="0" end_pos="636" is_yun="0" perr_level_msg="1" perr_msg="0" rec_node_type="paper" time_len="10"></phone>
                              <phone beg_pos="636" content="an" dp_message="0" end_pos="652" is_yun="1" mono_tone="TONE2" perr_level_msg="1" perr_msg="0" rec_node_type="paper" time_len="16"></phone>
                          </syll>
                      </word>
                      <word beg_pos="652" content="人" end_pos="684" symbol="ren7" time_len="32">
                          <syll beg_pos="652" content="人" dp_message="0" end_pos="684" rec_node_type="paper" symbol="ren0" time_len="32">
                              <phone beg_pos="652" content="r" dp_message="0" end_pos="662" is_yun="0" perr_level_msg="1" perr_msg="0" rec_node_type="paper" time_len="10"></phone>
                              <phone beg_pos="662" content="en" dp_message="0" end_pos="684" is_yun="1" mono_tone="TONE0" perr_level_msg="1" perr_msg="0" rec_node_type="paper" time_len="22"></phone>
                          </syll>
                      </word>
                  </sentence>
                  <sentence beg_pos="684" content="遇到什么事先想到的总是自己" end_pos="1059" fluency_score="0.000000" phone_score="100.000000" time_len="1059" tone_score="100.000000" total_score="92.398689">
                      <word beg_pos="684" content="遇" end_pos="744" symbol="yu4" time_len="60">
                          <syll beg_pos="684" content="sil" dp_message="0" end_pos="728" rec_node_type="sil" time_len="44">
                              <phone beg_pos="684" content="sil" dp_message="0" end_pos="728" rec_node_type="sil" time_len="44"></phone>
                          </syll>
                          <syll beg_pos="728" content="遇" dp_message="0" end_pos="744" rec_node_type="paper" symbol="yu4" time_len="16">
                              <phone beg_pos="728" content="_v" dp_message="0" end_pos="733" is_yun="0" perr_level_msg="1" perr_msg="0" rec_node_type="paper" time_len="5"></phone>
                              <phone beg_pos="733" content="v" dp_message="0" end_pos="744" is_yun="1" mono_tone="TONE4" perr_level_msg="1" perr_msg="0" rec_node_type="paper" time_len="11"></phone>
                          </syll>
                      </word>
                      <word beg_pos="744" content="到" end_pos="768" symbol="dao4" time_len="24">
                          <syll beg_pos="744" content="到" dp_message="0" end_pos="768" rec_node_type="paper" symbol="dao4" time_len="24">
                              <phone beg_pos="744" content="d" dp_message="0" end_pos="752" is_yun="0" perr_level_msg="2" perr_msg="0" rec_node_type="paper" time_len="8"></phone>
                              <phone beg_pos="752" content="ao" dp_message="0" end_pos="768" is_yun="1" mono_tone="TONE4" perr_level_msg="1" perr_msg="0" rec_node_type="paper" time_len="16"></phone>
                          </syll>
                      </word>
                      <word beg_pos="768" content="什" end_pos="786" symbol="shen2" time_len="18">
                          <syll beg_pos="768" content="什" dp_message="0" end_pos="786" rec_node_type="paper" symbol="shen2" time_len="18">
                              <phone beg_pos="768" content="sh" dp_message="0" end_pos="778" is_yun="0" perr_level_msg="1" perr_msg="0" rec_node_type="paper" time_len="10"></phone>
                              <phone beg_pos="778" content="en" dp_message="0" end_pos="786" is_yun="1" mono_tone="TONE2" perr_level_msg="1" perr_msg="0" rec_node_type="paper" time_len="8"></phone>
                          </syll>
                      </word>
                      <word beg_pos="786" content="么" end_pos="812" symbol="me5" time_len="26">
                          <syll beg_pos="786" content="么" dp_message="0" end_pos="812" rec_node_type="paper" symbol="me0" time_len="26">
                              <phone beg_pos="786" content="m" dp_message="0" end_pos="799" is_yun="0" perr_level_msg="1" perr_msg="0" rec_node_type="paper" time_len="13"></phone>
                              <phone beg_pos="799" content="e" dp_message="0" end_pos="812" is_yun="1" mono_tone="TONE0" perr_level_msg="1" perr_msg="0" rec_node_type="paper" time_len="13"></phone>
                          </syll>
                      </word>
                      <word beg_pos="812" content="事" end_pos="852" symbol="shi4" time_len="40">
                          <syll beg_pos="812" content="事" dp_message="0" end_pos="852" rec_node_type="paper" symbol="shi4" time_len="40">
                              <phone beg_pos="812" content="sh" dp_message="0" end_pos="828" is_yun="0" perr_level_msg="1" perr_msg="0" rec_node_type="paper" time_len="16"></phone>
                              <phone beg_pos="828" content="iii" dp_message="0" end_pos="852" is_yun="1" mono_tone="TONE4" perr_level_msg="1" perr_msg="0" rec_node_type="paper" time_len="24"></phone>
                          </syll>
                      </word>
                      <word beg_pos="852" content="先" end_pos="880" symbol="xian1" time_len="28">
                          <syll beg_pos="852" content="先" dp_message="0" end_pos="880" rec_node_type="paper" symbol="xian1" time_len="28">
                              <phone beg_pos="852" content="x" dp_message="0" end_pos="864" is_yun="0" perr_level_msg="1" perr_msg="0" rec_node_type="paper" time_len="12"></phone>
                              <phone beg_pos="864" content="ian" dp_message="0" end_pos="880" is_yun="1" mono_tone="TONE1" perr_level_msg="1" perr_msg="0" rec_node_type="paper" time_len="16"></phone>
                          </syll>
                      </word>
                      <word beg_pos="880" content="想" end_pos="914" symbol="xiang3" time_len="34">
                          <syll beg_pos="880" content="想" dp_message="0" end_pos="914" rec_node_type="paper" symbol="xiang3" time_len="34">
                              <phone beg_pos="880" content="x" dp_message="0" end_pos="892" is_yun="0" perr_level_msg="1" perr_msg="0" rec_node_type="paper" time_len="12"></phone>
                              <phone beg_pos="892" content="iang" dp_message="0" end_pos="914" is_yun="1" mono_tone="TONE3" perr_level_msg="1" perr_msg="0" rec_node_type="paper" time_len="22"></phone>
                          </syll>
                      </word>
                      <word beg_pos="914" content="到" end_pos="938" symbol="dao4" time_len="24">
                          <syll beg_pos="914" content="到" dp_message="0" end_pos="938" rec_node_type="paper" symbol="dao4" time_len="24">
                              <phone beg_pos="914" content="d" dp_message="0" end_pos="921" is_yun="0" perr_level_msg="1" perr_msg="0" rec_node_type="paper" time_len="7"></phone>
                              <phone beg_pos="921" content="ao" dp_message="0" end_pos="938" is_yun="1" mono_tone="TONE4" perr_level_msg="1" perr_msg="0" rec_node_type="paper" time_len="17"></phone>
                          </syll>
                      </word>
                      <word beg_pos="938" content="的" end_pos="958" symbol="de5" time_len="20">
                          <syll beg_pos="938" content="的" dp_message="0" end_pos="958" rec_node_type="paper" symbol="de0" time_len="20">
                              <phone beg_pos="938" content="d" dp_message="0" end_pos="942" is_yun="0" perr_level_msg="1" perr_msg="0" rec_node_type="paper" time_len="4"></phone>
                              <phone beg_pos="942" content="e" dp_message="0" end_pos="958" is_yun="1" mono_tone="TONE0" perr_level_msg="1" perr_msg="0" rec_node_type="paper" time_len="16"></phone>
                          </syll>
                      </word>
                      <word beg_pos="958" content="总" end_pos="984" symbol="zong3" time_len="26">
                          <syll beg_pos="958" content="总" dp_message="0" end_pos="984" rec_node_type="paper" symbol="zong3" time_len="26">
                              <phone beg_pos="958" content="z" dp_message="0" end_pos="968" is_yun="0" perr_level_msg="1" perr_msg="0" rec_node_type="paper" time_len="10"></phone>
                              <phone beg_pos="968" content="ong" dp_message="0" end_pos="984" is_yun="1" mono_tone="TONE3" perr_level_msg="1" perr_msg="0" rec_node_type="paper" time_len="16"></phone>
                          </syll>
                      </word>
                      <word beg_pos="984" content="是" end_pos="1006" symbol="shi4" time_len="22">
                          <syll beg_pos="984" content="是" dp_message="0" end_pos="1006" rec_node_type="paper" symbol="shi4" time_len="22">
                              <phone beg_pos="984" content="sh" dp_message="0" end_pos="998" is_yun="0" perr_level_msg="1" perr_msg="0" rec_node_type="paper" time_len="14"></phone>
                              <phone beg_pos="998" content="iii" dp_message="0" end_pos="1006" is_yun="1" mono_tone="TONE4" perr_level_msg="2" perr_msg="0" rec_node_type="paper" time_len="8"></phone>
                          </syll>
                      </word>
                      <word beg_pos="1006" content="自" end_pos="1032" symbol="zi4" time_len="26">
                          <syll beg_pos="1006" content="自" dp_message="0" end_pos="1032" rec_node_type="paper" symbol="zi4" time_len="26">
                              <phone beg_pos="1006" content="z" dp_message="0" end_pos="1020" is_yun="0" perr_level_msg="1" perr_msg="0" rec_node_type="paper" time_len="14"></phone>
                              <phone beg_pos="1020" content="ii" dp_message="0" end_pos="1032" is_yun="1" mono_tone="TONE4" perr_level_msg="1" perr_msg="0" rec_node_type="paper" time_len="12"></phone>
                          </syll>
                      </word>
                      <word beg_pos="1032" content="己" end_pos="1059" symbol="ji3" time_len="27">
                          <syll beg_pos="1032" content="己" dp_message="0" end_pos="1059" rec_node_type="paper" symbol="ji3" time_len="27">
                              <phone beg_pos="1032" content="j" dp_message="0" end_pos="1043" is_yun="0" perr_level_msg="1" perr_msg="0" rec_node_type="paper" time_len="11"></phone>
                              <phone beg_pos="1043" content="i" dp_message="0" end_pos="1059" is_yun="1" mono_tone="TONE3" perr_level_msg="1" perr_msg="0" rec_node_type="paper" time_len="16"></phone>
                          </syll>
                      </word>
                  </sentence>
                  <sentence beg_pos="1059" content="这样的人靠不住" end_pos="1265" fluency_score="0.000000" phone_score="100.000000" time_len="1265" tone_score="100.000000" total_score="92.398689">
                      <word beg_pos="1059" content="这" end_pos="1110" symbol="zhe4" time_len="51">
                          <syll beg_pos="1059" content="fil" dp_message="32" end_pos="1088" rec_node_type="fil" time_len="29">
                              <phone beg_pos="1059" content="fil" dp_message="32" end_pos="1088" rec_node_type="fil" time_len="29"></phone>
                          </syll>
                          <syll beg_pos="1088" content="这" dp_message="0" end_pos="1110" rec_node_type="paper" symbol="zhe4" time_len="22">
                              <phone beg_pos="1088" content="zh" dp_message="0" end_pos="1105" is_yun="0" perr_level_msg="1" perr_msg="0" rec_node_type="paper" time_len="17"></phone>
                              <phone beg_pos="1105" content="e" dp_message="0" end_pos="1110" is_yun="1" mono_tone="TONE4" perr_level_msg="1" perr_msg="0" rec_node_type="paper" time_len="5"></phone>
                          </syll>
                      </word>
                      <word beg_pos="1110" content="样" end_pos="1136" symbol="yang9" time_len="26">
                          <syll beg_pos="1110" content="样" dp_message="0" end_pos="1136" rec_node_type="paper" symbol="yang0" time_len="26">
                              <phone beg_pos="1110" content="_i" dp_message="0" end_pos="1117" is_yun="0" perr_level_msg="1" perr_msg="0" rec_node_type="paper" time_len="7"></phone>
                              <phone beg_pos="1117" content="iang" dp_message="0" end_pos="1136" is_yun="1" mono_tone="TONE0" perr_level_msg="1" perr_msg="0" rec_node_type="paper" time_len="19"></phone>
                          </syll>
                      </word>
                      <word beg_pos="1136" content="的" end_pos="1156" symbol="de5" time_len="20">
                          <syll beg_pos="1136" content="的" dp_message="0" end_pos="1156" rec_node_type="paper" symbol="de0" time_len="20">
                              <phone beg_pos="1136" content="d" dp_message="0" end_pos="1141" is_yun="0" perr_level_msg="1" perr_msg="0" rec_node_type="paper" time_len="5"></phone>
                              <phone beg_pos="1141" content="e" dp_message="0" end_pos="1156" is_yun="1" mono_tone="TONE0" perr_level_msg="1" perr_msg="0" rec_node_type="paper" time_len="15"></phone>
                          </syll>
                      </word>
                      <word beg_pos="1156" content="人" end_pos="1178" symbol="ren2" time_len="22">
                          <syll beg_pos="1156" content="人" dp_message="0" end_pos="1178" rec_node_type="paper" symbol="ren2" time_len="22">
                              <phone beg_pos="1156" content="r" dp_message="0" end_pos="1164" is_yun="0" perr_level_msg="1" perr_msg="0" rec_node_type="paper" time_len="8"></phone>
                              <phone beg_pos="1164" content="en" dp_message="0" end_pos="1178" is_yun="1" mono_tone="TONE2" perr_level_msg="1" perr_msg="0" rec_node_type="paper" time_len="14"></phone>
                          </syll>
                      </word>
                      <word beg_pos="1178" content="靠" end_pos="1202" symbol="kao4" time_len="24">
                          <syll beg_pos="1178" content="靠" dp_message="0" end_pos="1202" rec_node_type="paper" symbol="kao4" time_len="24">
                              <phone beg_pos="1178" content="k" dp_message="0" end_pos="1188" is_yun="0" perr_level_msg="1" perr_msg="0" rec_node_type="paper" time_len="10"></phone>
                              <phone beg_pos="1188" content="ao" dp_message="0" end_pos="1202" is_yun="1" mono_tone="TONE4" perr_level_msg="1" perr_msg="0" rec_node_type="paper" time_len="14"></phone>
                          </syll>
                      </word>
                      <word beg_pos="1202" content="不" end_pos="1228" symbol="bu2" time_len="26">
                          <syll beg_pos="1202" content="不" dp_message="0" end_pos="1228" rec_node_type="paper" symbol="bu2" time_len="26">
                              <phone beg_pos="1202" content="b" dp_message="0" end_pos="1213" is_yun="0" perr_level_msg="1" perr_msg="0" rec_node_type="paper" time_len="11"></phone>
                              <phone beg_pos="1213" content="u" dp_message="0" end_pos="1228" is_yun="1" mono_tone="TONE2" perr_level_msg="1" perr_msg="0" rec_node_type="paper" time_len="15"></phone>
                          </syll>
                      </word>
                      <word beg_pos="1228" content="住" end_pos="1265" symbol="zhu4" time_len="37">
                          <syll beg_pos="1228" content="住" dp_message="0" end_pos="1265" rec_node_type="paper" symbol="zhu4" time_len="37">
                              <phone beg_pos="1228" content="zh" dp_message="0" end_pos="1240" is_yun="0" perr_level_msg="1" perr_msg="0" rec_node_type="paper" time_len="12"></phone>
                              <phone beg_pos="1240" content="u" dp_message="0" end_pos="1265" is_yun="1" mono_tone="TONE4" perr_level_msg="1" perr_msg="0" rec_node_type="paper" time_len="25"></phone>
                          </syll>
                      </word>
                  </sentence>
                  <sentence beg_pos="1265" content="我妈说我太理想化" end_pos="1502" fluency_score="0.000000" phone_score="100.000000" time_len="1502" tone_score="75.000000" total_score="92.398689">
                      <word beg_pos="1265" content="我" end_pos="1312" symbol="wo3" time_len="47">
                          <syll beg_pos="1265" content="sil" dp_message="0" end_pos="1268" rec_node_type="sil" time_len="3">
                              <phone beg_pos="1265" content="sil" dp_message="0" end_pos="1268" rec_node_type="sil" time_len="3"></phone>
                          </syll>
                          <syll beg_pos="1268" content="我" dp_message="0" end_pos="1312" rec_node_type="paper" symbol="wo3" time_len="44">
                              <phone beg_pos="1268" content="_u" dp_message="0" end_pos="1304" is_yun="0" perr_level_msg="1" perr_msg="0" rec_node_type="paper" time_len="36"></phone>
                              <phone beg_pos="1304" content="uo" dp_message="0" end_pos="1312" is_yun="1" mono_tone="TONE3" perr_level_msg="1" perr_msg="0" rec_node_type="paper" time_len="8"></phone>
                          </syll>
                      </word>
                      <word beg_pos="1312" content="妈" end_pos="1338" symbol="ma1" time_len="26">
                          <syll beg_pos="1312" content="妈" dp_message="0" end_pos="1338" rec_node_type="paper" symbol="ma1" time_len="26">
                              <phone beg_pos="1312" content="m" dp_message="0" end_pos="1323" is_yun="0" perr_level_msg="1" perr_msg="0" rec_node_type="paper" time_len="11"></phone>
                              <phone beg_pos="1323" content="a" dp_message="0" end_pos="1338" is_yun="1" mono_tone="TONE1" perr_level_msg="1" perr_msg="0" rec_node_type="paper" time_len="15"></phone>
                          </syll>
                      </word>
                      <word beg_pos="1338" content="说" end_pos="1361" symbol="shuo1" time_len="23">
                          <syll beg_pos="1338" content="说" dp_message="0" end_pos="1361" rec_node_type="paper" symbol="shuo1" time_len="23">
                              <phone beg_pos="1338" content="sh" dp_message="0" end_pos="1352" is_yun="0" perr_level_msg="1" perr_msg="0" rec_node_type="paper" time_len="14"></phone>
                              <phone beg_pos="1352" content="uo" dp_message="0" end_pos="1361" is_yun="1" mono_tone="TONE1" perr_level_msg="1" perr_msg="0" rec_node_type="paper" time_len="9"></phone>
                          </syll>
                      </word>
                      <word beg_pos="1361" content="我" end_pos="1382" symbol="wo3" time_len="21">
                          <syll beg_pos="1361" content="我" dp_message="0" end_pos="1382" rec_node_type="paper" symbol="wo3" time_len="21">
                              <phone beg_pos="1361" content="_u" dp_message="0" end_pos="1370" is_yun="0" perr_level_msg="1" perr_msg="0" rec_node_type="paper" time_len="9"></phone>
                              <phone beg_pos="1370" content="uo" dp_message="0" end_pos="1382" is_yun="1" mono_tone="TONE3" perr_level_msg="1" perr_msg="0" rec_node_type="paper" time_len="12"></phone>
                          </syll>
                      </word>
                      <word beg_pos="1382" content="太" end_pos="1412" symbol="tai4" time_len="30">
                          <syll beg_pos="1382" content="太" dp_message="0" end_pos="1412" rec_node_type="paper" symbol="tai4" time_len="30">
                              <phone beg_pos="1382" content="t" dp_message="0" end_pos="1396" is_yun="0" perr_level_msg="1" perr_msg="0" rec_node_type="paper" time_len="14"></phone>
                              <phone beg_pos="1396" content="ai" dp_message="0" end_pos="1412" is_yun="1" mono_tone="TONE4" perr_level_msg="1" perr_msg="2" rec_node_type="paper" time_len="16"></phone>
                          </syll>
                      </word>
                      <word beg_pos="1412" content="理" end_pos="1434" symbol="li2" time_len="22">
                          <syll beg_pos="1412" content="理" dp_message="0" end_pos="1434" rec_node_type="paper" symbol="li2" time_len="22">
                              <phone beg_pos="1412" content="l" dp_message="0" end_pos="1420" is_yun="0" perr_level_msg="1" perr_msg="0" rec_node_type="paper" time_len="8"></phone>
                              <phone beg_pos="1420" content="i" dp_message="0" end_pos="1434" is_yun="1" mono_tone="TONE2" perr_level_msg="1" perr_msg="0" rec_node_type="paper" time_len="14"></phone>
                          </syll>
                      </word>
                      <word beg_pos="1434" content="想" end_pos="1464" symbol="xiang3" time_len="30">
                          <syll beg_pos="1434" content="想" dp_message="0" end_pos="1464" rec_node_type="paper" symbol="xiang3" time_len="30">
                              <phone beg_pos="1434" content="x" dp_message="0" end_pos="1446" is_yun="0" perr_level_msg="1" perr_msg="0" rec_node_type="paper" time_len="12"></phone>
                              <phone beg_pos="1446" content="iang" dp_message="0" end_pos="1464" is_yun="1" mono_tone="TONE3" perr_level_msg="1" perr_msg="0" rec_node_type="paper" time_len="18"></phone>
                          </syll>
                      </word>
                      <word beg_pos="1464" content="化" end_pos="1502" symbol="hua4" time_len="38">
                          <syll beg_pos="1464" content="化" dp_message="0" end_pos="1502" rec_node_type="paper" symbol="hua4" time_len="38">
                              <phone beg_pos="1464" content="h" dp_message="0" end_pos="1476" is_yun="0" perr_level_msg="1" perr_msg="0" rec_node_type="paper" time_len="12"></phone>
                              <phone beg_pos="1476" content="ua" dp_message="0" end_pos="1502" is_yun="1" mono_tone="TONE4" perr_level_msg="1" perr_msg="2" rec_node_type="paper" time_len="26"></phone>
                          </syll>
                      </word>
                  </sentence>
                  <sentence beg_pos="1502" content="可这种大事我可不想马马虎虎的" end_pos="1876" fluency_score="0.000000" phone_score="100.000000" time_len="1876" tone_score="78.571426" total_score="92.398689">
                      <word beg_pos="1502" content="可" end_pos="1558" symbol="ke3" time_len="56">
                          <syll beg_pos="1502" content="sil" dp_message="0" end_pos="1528" rec_node_type="sil" time_len="26">
                              <phone beg_pos="1502" content="sil" dp_message="0" end_pos="1528" rec_node_type="sil" time_len="26"></phone>
                          </syll>
                          <syll beg_pos="1528" content="可" dp_message="0" end_pos="1558" rec_node_type="paper" symbol="ke3" time_len="30">
                              <phone beg_pos="1528" content="k" dp_message="0" end_pos="1544" is_yun="0" perr_level_msg="1" perr_msg="0" rec_node_type="paper" time_len="16"></phone>
                              <phone beg_pos="1544" content="e" dp_message="0" end_pos="1558" is_yun="1" mono_tone="TONE3" perr_level_msg="1" perr_msg="2" rec_node_type="paper" time_len="14"></phone>
                          </syll>
                      </word>
                      <word beg_pos="1558" content="这" end_pos="1584" symbol="zhe4" time_len="26">
                          <syll beg_pos="1558" content="这" dp_message="0" end_pos="1584" rec_node_type="paper" symbol="zhe4" time_len="26">
                              <phone beg_pos="1558" content="zh" dp_message="0" end_pos="1566" is_yun="0" perr_level_msg="1" perr_msg="0" rec_node_type="paper" time_len="8"></phone>
                              <phone beg_pos="1566" content="e" dp_message="0" end_pos="1584" is_yun="1" mono_tone="TONE4" perr_level_msg="1" perr_msg="0" rec_node_type="paper" time_len="18"></phone>
                          </syll>
                      </word>
                      <word beg_pos="1584" content="种" end_pos="1610" symbol="zhong3" time_len="26">
                          <syll beg_pos="1584" content="种" dp_message="0" end_pos="1610" rec_node_type="paper" symbol="zhong3" time_len="26">
                              <phone beg_pos="1584" content="zh" dp_message="0" end_pos="1594" is_yun="0" perr_level_msg="1" perr_msg="0" rec_node_type="paper" time_len="10"></phone>
                              <phone beg_pos="1594" content="ong" dp_message="0" end_pos="1610" is_yun="1" mono_tone="TONE3" perr_level_msg="1" perr_msg="0" rec_node_type="paper" time_len="16"></phone>
                          </syll>
                      </word>
                      <word beg_pos="1610" content="大" end_pos="1634" symbol="da4" time_len="24">
                          <syll beg_pos="1610" content="大" dp_message="0" end_pos="1634" rec_node_type="paper" symbol="da4" time_len="24">
                              <phone beg_pos="1610" content="d" dp_message="0" end_pos="1618" is_yun="0" perr_level_msg="1" perr_msg="0" rec_node_type="paper" time_len="8"></phone>
                              <phone beg_pos="1618" content="a" dp_message="0" end_pos="1634" is_yun="1" mono_tone="TONE4" perr_level_msg="1" perr_msg="0" rec_node_type="paper" time_len="16"></phone>
                          </syll>
                      </word>
                      <word beg_pos="1634" content="事" end_pos="1662" symbol="shi4" time_len="28">
                          <syll beg_pos="1634" content="事" dp_message="0" end_pos="1662" rec_node_type="paper" symbol="shi4" time_len="28">
                              <phone beg_pos="1634" content="sh" dp_message="0" end_pos="1650" is_yun="0" perr_level_msg="1" perr_msg="0" rec_node_type="paper" time_len="16"></phone>
                              <phone beg_pos="1650" content="iii" dp_message="0" end_pos="1662" is_yun="1" mono_tone="TONE4" perr_level_msg="1" perr_msg="2" rec_node_type="paper" time_len="12"></phone>
                          </syll>
                      </word>
                      <word beg_pos="1662" content="我" end_pos="1682" symbol="wo3" time_len="20">
                          <syll beg_pos="1662" content="我" dp_message="0" end_pos="1682" rec_node_type="paper" symbol="wo3" time_len="20">
                              <phone beg_pos="1662" content="_u" dp_message="0" end_pos="1670" is_yun="0" perr_level_msg="1" perr_msg="0" rec_node_type="paper" time_len="8"></phone>
                              <phone beg_pos="1670" content="uo" dp_message="0" end_pos="1682" is_yun="1" mono_tone="TONE3" perr_level_msg="1" perr_msg="0" rec_node_type="paper" time_len="12"></phone>
                          </syll>
                      </word>
                      <word beg_pos="1682" content="可" end_pos="1708" symbol="ke3" time_len="26">
                          <syll beg_pos="1682" content="可" dp_message="0" end_pos="1708" rec_node_type="paper" symbol="ke3" time_len="26">
                              <phone beg_pos="1682" content="k" dp_message="0" end_pos="1698" is_yun="0" perr_level_msg="1" perr_msg="0" rec_node_type="paper" time_len="16"></phone>
                              <phone beg_pos="1698" content="e" dp_message="0" end_pos="1708" is_yun="1" mono_tone="TONE3" perr_level_msg="1" perr_msg="0" rec_node_type="paper" time_len="10"></phone>
                          </syll>
                      </word>
                      <word beg_pos="1708" content="不" end_pos="1728" symbol="bu4" time_len="20">
                          <syll beg_pos="1708" content="不" dp_message="0" end_pos="1728" rec_node_type="paper" symbol="bu4" time_len="20">
                              <phone beg_pos="1708" content="b" dp_message="0" end_pos="1719" is_yun="0" perr_level_msg="1" perr_msg="0" rec_node_type="paper" time_len="11"></phone>
                              <phone beg_pos="1719" content="u" dp_message="0" end_pos="1728" is_yun="1" mono_tone="TONE4" perr_level_msg="1" perr_msg="0" rec_node_type="paper" time_len="9"></phone>
                          </syll>
                      </word>
                      <word beg_pos="1728" content="想" end_pos="1752" symbol="xiang3" time_len="24">
                          <syll beg_pos="1728" content="想" dp_message="0" end_pos="1752" rec_node_type="paper" symbol="xiang3" time_len="24">
                              <phone beg_pos="1728" content="x" dp_message="0" end_pos="1740" is_yun="0" perr_level_msg="1" perr_msg="0" rec_node_type="paper" time_len="12"></phone>
                              <phone beg_pos="1740" content="iang" dp_message="0" end_pos="1752" is_yun="1" mono_tone="TONE3" perr_level_msg="1" perr_msg="0" rec_node_type="paper" time_len="12"></phone>
                          </syll>
                      </word>
                      <word beg_pos="1752" content="马" end_pos="1778" symbol="ma2" time_len="26">
                          <syll beg_pos="1752" content="马" dp_message="0" end_pos="1778" rec_node_type="paper" symbol="ma2" time_len="26">
                              <phone beg_pos="1752" content="m" dp_message="0" end_pos="1764" is_yun="0" perr_level_msg="1" perr_msg="0" rec_node_type="paper" time_len="12"></phone>
                              <phone beg_pos="1764" content="a" dp_message="0" end_pos="1778" is_yun="1" mono_tone="TONE2" perr_level_msg="1" perr_msg="0" rec_node_type="paper" time_len="14"></phone>
                          </syll>
                      </word>
                      <word beg_pos="1778" content="马" end_pos="1796" symbol="ma3" time_len="18">
                          <syll beg_pos="1778" content="马" dp_message="0" end_pos="1796" rec_node_type="paper" symbol="ma3" time_len="18">
                              <phone beg_pos="1778" content="m" dp_message="0" end_pos="1788" is_yun="0" perr_level_msg="1" perr_msg="0" rec_node_type="paper" time_len="10"></phone>
                              <phone beg_pos="1788" content="a" dp_message="0" end_pos="1796" is_yun="1" mono_tone="TONE3" perr_level_msg="1" perr_msg="2" rec_node_type="paper" time_len="8"></phone>
                          </syll>
                      </word>
                      <word beg_pos="1796" content="虎" end_pos="1824" symbol="hu1" time_len="28">
                          <syll beg_pos="1796" content="虎" dp_message="0" end_pos="1824" rec_node_type="paper" symbol="hu1" time_len="28">
                              <phone beg_pos="1796" content="h" dp_message="0" end_pos="1818" is_yun="0" perr_level_msg="1" perr_msg="0" rec_node_type="paper" time_len="22"></phone>
                              <phone beg_pos="1818" content="u" dp_message="0" end_pos="1824" is_yun="1" mono_tone="TONE1" perr_level_msg="1" perr_msg="0" rec_node_type="paper" time_len="6"></phone>
                          </syll>
                      </word>
                      <word beg_pos="1824" content="虎" end_pos="1852" symbol="hu1" time_len="28">
                          <syll beg_pos="1824" content="虎" dp_message="0" end_pos="1852" rec_node_type="paper" symbol="hu1" time_len="28">
                              <phone beg_pos="1824" content="h" dp_message="0" end_pos="1838" is_yun="0" perr_level_msg="1" perr_msg="0" rec_node_type="paper" time_len="14"></phone>
                              <phone beg_pos="1838" content="u" dp_message="0" end_pos="1852" is_yun="1" mono_tone="TONE1" perr_level_msg="1" perr_msg="0" rec_node_type="paper" time_len="14"></phone>
                          </syll>
                      </word>
                      <word beg_pos="1852" content="的" end_pos="1876" symbol="de5" time_len="24">
                          <syll beg_pos="1852" content="的" dp_message="0" end_pos="1876" rec_node_type="paper" symbol="de0" time_len="24">
                              <phone beg_pos="1852" content="d" dp_message="0" end_pos="1856" is_yun="0" perr_level_msg="2" perr_msg="0" rec_node_type="paper" time_len="4"></phone>
                              <phone beg_pos="1856" content="e" dp_message="0" end_pos="1876" is_yun="1" mono_tone="TONE0" perr_level_msg="1" perr_msg="0" rec_node_type="paper" time_len="20"></phone>
                          </syll>
                      </word>
                  </sentence>
                  <sentence beg_pos="1876" content="要找就找个称心如意的" end_pos="2204" fluency_score="0.000000" phone_score="85.000000" time_len="2204" tone_score="70.000000" total_score="79.757721">
                      <word beg_pos="1876" content="要" end_pos="1946" symbol="yao4" time_len="70">
                          <syll beg_pos="1876" content="fil" dp_message="32" end_pos="1882" rec_node_type="fil" time_len="6">
                              <phone beg_pos="1876" content="fil" dp_message="32" end_pos="1882" rec_node_type="fil" time_len="6"></phone>
                          </syll>
                          <syll beg_pos="1882" content="sil" dp_message="0" end_pos="1914" rec_node_type="sil" time_len="32">
                              <phone beg_pos="1882" content="sil" dp_message="0" end_pos="1914" rec_node_type="sil" time_len="32"></phone>
                          </syll>
                          <syll beg_pos="1914" content="要" dp_message="0" end_pos="1946" rec_node_type="paper" symbol="yao4" time_len="32">
                              <phone beg_pos="1914" content="_i" dp_message="0" end_pos="1928" is_yun="0" perr_level_msg="1" perr_msg="0" rec_node_type="paper" time_len="14"></phone>
                              <phone beg_pos="1928" content="iao" dp_message="0" end_pos="1946" is_yun="1" mono_tone="TONE4" perr_level_msg="1" perr_msg="0" rec_node_type="paper" time_len="18"></phone>
                          </syll>
                      </word>
                      <word beg_pos="1946" content="找" end_pos="1974" symbol="zhao3" time_len="28">
                          <syll beg_pos="1946" content="找" dp_message="0" end_pos="1974" rec_node_type="paper" symbol="zhao3" time_len="28">
                              <phone beg_pos="1946" content="zh" dp_message="0" end_pos="1955" is_yun="0" perr_level_msg="1" perr_msg="0" rec_node_type="paper" time_len="9"></phone>
                              <phone beg_pos="1955" content="ao" dp_message="0" end_pos="1974" is_yun="1" mono_tone="TONE3" perr_level_msg="1" perr_msg="0" rec_node_type="paper" time_len="19"></phone>
                          </syll>
                      </word>
                      <word beg_pos="1974" content="就" end_pos="2016" symbol="jiu4" time_len="42">
                          <syll beg_pos="1974" content="就" dp_message="0" end_pos="2016" rec_node_type="paper" symbol="jiu4" time_len="42">
                              <phone beg_pos="1974" content="j" dp_message="0" end_pos="1983" is_yun="0" perr_level_msg="3" perr_msg="1" rec_node_type="paper" time_len="9"></phone>
                              <phone beg_pos="1983" content="iou" dp_message="0" end_pos="2016" is_yun="1" mono_tone="TONE4" perr_level_msg="1" perr_msg="2" rec_node_type="paper" time_len="33"></phone>
                          </syll>
                      </word>
                      <word beg_pos="2016" content="找" end_pos="2044" symbol="zhao3" time_len="28">
                          <syll beg_pos="2016" content="找" dp_message="0" end_pos="2044" rec_node_type="paper" symbol="zhao3" time_len="28">
                              <phone beg_pos="2016" content="zh" dp_message="0" end_pos="2025" is_yun="0" perr_level_msg="1" perr_msg="0" rec_node_type="paper" time_len="9"></phone>
                              <phone beg_pos="2025" content="ao" dp_message="0" end_pos="2044" is_yun="1" mono_tone="TONE3" perr_level_msg="1" perr_msg="0" rec_node_type="paper" time_len="19"></phone>
                          </syll>
                      </word>
                      <word beg_pos="2044" content="个" end_pos="2060" symbol="ge4" time_len="16">
                          <syll beg_pos="2044" content="个" dp_message="0" end_pos="2060" rec_node_type="paper" symbol="ge4" time_len="16">
                              <phone beg_pos="2044" content="g" dp_message="0" end_pos="2050" is_yun="0" perr_level_msg="3" perr_msg="1" rec_node_type="paper" time_len="6"></phone>
                              <phone beg_pos="2050" content="e" dp_message="0" end_pos="2060" is_yun="1" mono_tone="TONE4" perr_level_msg="3" perr_msg="1" rec_node_type="paper" time_len="10"></phone>
                          </syll>
                      </word>
                      <word beg_pos="2060" content="称" end_pos="2094" symbol="chen4" time_len="34">
                          <syll beg_pos="2060" content="称" dp_message="0" end_pos="2094" rec_node_type="paper" symbol="chen4" time_len="34">
                              <phone beg_pos="2060" content="ch" dp_message="0" end_pos="2076" is_yun="0" perr_level_msg="1" perr_msg="0" rec_node_type="paper" time_len="16"></phone>
                              <phone beg_pos="2076" content="en" dp_message="0" end_pos="2094" is_yun="1" mono_tone="TONE4" perr_level_msg="1" perr_msg="2" rec_node_type="paper" time_len="18"></phone>
                          </syll>
                      </word>
                      <word beg_pos="2094" content="心" end_pos="2120" symbol="xin1" time_len="26">
                          <syll beg_pos="2094" content="心" dp_message="0" end_pos="2120" rec_node_type="paper" symbol="xin1" time_len="26">
                              <phone beg_pos="2094" content="x" dp_message="0" end_pos="2110" is_yun="0" perr_level_msg="1" perr_msg="0" rec_node_type="paper" time_len="16"></phone>
                              <phone beg_pos="2110" content="in" dp_message="0" end_pos="2120" is_yun="1" mono_tone="TONE1" perr_level_msg="1" perr_msg="0" rec_node_type="paper" time_len="10"></phone>
                          </syll>
                      </word>
                      <word beg_pos="2120" content="如" end_pos="2162" symbol="ru2" time_len="42">
                          <syll beg_pos="2120" content="如" dp_message="0" end_pos="2162" rec_node_type="paper" symbol="ru2" time_len="42">
                              <phone beg_pos="2120" content="r" dp_message="0" end_pos="2148" is_yun="0" perr_level_msg="1" perr_msg="0" rec_node_type="paper" time_len="28"></phone>
                              <phone beg_pos="2148" content="u" dp_message="0" end_pos="2162" is_yun="1" mono_tone="TONE2" perr_level_msg="1" perr_msg="0" rec_node_type="paper" time_len="14"></phone>
                          </syll>
                      </word>
                      <word beg_pos="2162" content="意" end_pos="2190" symbol="yi4" time_len="28">
                          <syll beg_pos="2162" content="意" dp_message="0" end_pos="2190" rec_node_type="paper" symbol="yi4" time_len="28">
                              <phone beg_pos="2162" content="_i" dp_message="0" end_pos="2172" is_yun="0" perr_level_msg="1" perr_msg="0" rec_node_type="paper" time_len="10"></phone>
                              <phone beg_pos="2172" content="i" dp_message="0" end_pos="2190" is_yun="1" mono_tone="TONE4" perr_level_msg="1" perr_msg="2" rec_node_type="paper" time_len="18"></phone>
                          </syll>
                      </word>
                      <word beg_pos="2190" content="的" end_pos="2204" symbol="de5" time_len="14">
                          <syll beg_pos="2190" content="的" dp_message="0" end_pos="2204" rec_node_type="paper" symbol="de0" time_len="14">
                              <phone beg_pos="2190" content="d" dp_message="0" end_pos="2198" is_yun="0" perr_level_msg="1" perr_msg="0" rec_node_type="paper" time_len="8"></phone>
                              <phone beg_pos="2198" content="e" dp_message="0" end_pos="2204" is_yun="1" mono_tone="TONE0" perr_level_msg="1" perr_msg="0" rec_node_type="paper" time_len="6"></phone>
                          </syll>
                      </word>
                  </sentence>
                  <sentence beg_pos="2204" content="你说是吧" end_pos="2373" fluency_score="0.000000" phone_score="87.500000" time_len="2373" tone_score="50.000000" total_score="81.652840">
                      <word beg_pos="2204" content="你" end_pos="2242" symbol="ni3" time_len="38">
                          <syll beg_pos="2204" content="fil" dp_message="32" end_pos="2227" rec_node_type="fil" time_len="23">
                              <phone beg_pos="2204" content="fil" dp_message="32" end_pos="2227" rec_node_type="fil" time_len="23"></phone>
                          </syll>
                          <syll beg_pos="2227" content="你" dp_message="0" end_pos="2242" rec_node_type="paper" symbol="ni3" time_len="15">
                              <phone beg_pos="2227" content="n" dp_message="0" end_pos="2230" is_yun="0" perr_level_msg="3" perr_msg="1" rec_node_type="paper" time_len="3"></phone>
                              <phone beg_pos="2230" content="i" dp_message="0" end_pos="2242" is_yun="1" mono_tone="TONE3" perr_level_msg="1" perr_msg="2" rec_node_type="paper" time_len="12"></phone>
                          </syll>
                      </word>
                      <word beg_pos="2242" content="说" end_pos="2272" symbol="shuo1" time_len="30">
                          <syll beg_pos="2242" content="说" dp_message="0" end_pos="2272" rec_node_type="paper" symbol="shuo1" time_len="30">
                              <phone beg_pos="2242" content="sh" dp_message="0" end_pos="2256" is_yun="0" perr_level_msg="1" perr_msg="0" rec_node_type="paper" time_len="14"></phone>
                              <phone beg_pos="2256" content="uo" dp_message="0" end_pos="2272" is_yun="1" mono_tone="TONE1" perr_level_msg="1" perr_msg="0" rec_node_type="paper" time_len="16"></phone>
                          </syll>
                      </word>
                      <word beg_pos="2272" content="是" end_pos="2294" symbol="shi4" time_len="22">
                          <syll beg_pos="2272" content="是" dp_message="0" end_pos="2294" rec_node_type="paper" symbol="shi4" time_len="22">
                              <phone beg_pos="2272" content="sh" dp_message="0" end_pos="2284" is_yun="0" perr_level_msg="1" perr_msg="0" rec_node_type="paper" time_len="12"></phone>
                              <phone beg_pos="2284" content="iii" dp_message="0" end_pos="2294" is_yun="1" mono_tone="TONE4" perr_level_msg="1" perr_msg="2" rec_node_type="paper" time_len="10"></phone>
                          </syll>
                      </word>
                      <word beg_pos="2294" content="吧" end_pos="2373" symbol="ba5" time_len="79">
                          <syll beg_pos="2294" content="吧" dp_message="0" end_pos="2332" rec_node_type="paper" symbol="ba0" time_len="38">
                              <phone beg_pos="2294" content="b" dp_message="0" end_pos="2304" is_yun="0" perr_level_msg="1" perr_msg="0" rec_node_type="paper" time_len="10"></phone>
                              <phone beg_pos="2304" content="a" dp_message="0" end_pos="2332" is_yun="1" mono_tone="TONE0" perr_level_msg="1" perr_msg="0" rec_node_type="paper" time_len="28"></phone>
                          </syll>
                          <syll beg_pos="2332" content="sil" dp_message="0" end_pos="2352" rec_node_type="sil" time_len="20">
                              <phone beg_pos="2332" content="sil" end_pos="2352" time_len="20"></phone>
                          </syll>
                          <syll beg_pos="2352" content="fil" dp_message="32" end_pos="2373" rec_node_type="fil" time_len="21">
                              <phone beg_pos="2352" content="fil" end_pos="2373" time_len="21"></phone>
                          </syll>
                      </word>
                  </sentence>
              </read_sentence>
          </rec_paper>
      </read_sentence>
  </xml_result>